[
  {
    "title": "Yago oproprio",
    "image": "https://raw.githubusercontent.com/devduque/Data-App/main/assets/images/EventImage.png",
    "type": "musical",
    "availability": "16/05/2025 à 22/05/2025",
    "link": "https://yagooproprio.com"
  },
  {
    "title": "Romeu & Julieta",
    "image": "https://raw.githubusercontent.com/devduque/Data-App/main/assets/images/EventImage.png",
    "type": "teather",
    "availability": "12/05/2025 à 23/05/2025",
    "link": "https://yagooproprio.com"
  }
]
